[
    {
      "id": 0,
      "firstName": "harry",
      "lastName": "codewithharry",
      "maidenName": "shubham",
      "age": 30,
      "gender": "male",
      "email": "harry@codewithharry@gmail.com"
      },
    {
      "id": 1,
      "firstName": "Terry",
      "lastName": "Medhurst",
      "maidenName": "Smitham",
      "age": 50,
      "gender": "male",
      "email": "atuny0@sohu.com"
      },
    {
      "id": 2,
      "firstName": "Sheldon",
      "lastName": "Quigley",
      "maidenName": "Cole",
      "age": 28,
      "gender": "male",
      "email": "hbingley1@plala.or.jp"},
    {
      "id": 3,
      "firstName": "Terrill",
      "lastName": "Hills",
      "maidenName": "Hoeger",
      "age": 38,
      "gender": "male",
      "email": "rshawe2@51.la"},
    {
      "id": 4,
      "firstName": "Miles",
      "lastName": "Cummerata",
      "maidenName": "Maggio",
      "age": 49,
      "gender": "male",
      "email": "yraigatt3@nature.com"
      },
    {
      "id": 5,
      "firstName": "Mavis",
      "lastName": "Schultz",
      "maidenName": "Yundt",
      "age": 38,
      "gender": "male",
      "email": "kmeus4@upenn.edu"
     },
    {
      "id": 6,
      "firstName": "Alison",
      "lastName": "Reichert",
      "maidenName": "Franecki",
      "age": 21,
      "gender": "female",
      "email": "jtreleven5@nhs.uk",
      "phone": "+351 527 735 3642"},
    {
      "id": 7,
      "firstName": "Oleta",
      "lastName": "Abbott",
      "maidenName": "Wyman",
      "age": 31,
      "gender": "female",
      "email": "dpettegre6@columbia.edu"},
    {
      "id": 8,
      "firstName": "Ewell",
      "lastName": "Mueller",
      "maidenName": "Durgan",
      "age": 29,
      "gender": "male",
      "email": "ggude7@chron.com" },
    {
      "id": 9,
      "firstName": "Demetrius",
      "lastName": "Corkery",
      "maidenName": "Gleason",
      "age": 22,
      "gender": "male",
      "email": "nloiterton8@aol.com"},
    {
      "id": 10,
      "firstName": "Eleanora",
      "lastName": "Price",
      "maidenName": "Cummings",
      "age": 37,
      "gender": "female",
      "email": "umcgourty9@jalbum.net"
      }]